genderator/__init__.py
genderator/normalizr.py
genderator/parser.py
genderator/data/name_surname_ratio.tsv
genderator/data/names_ine.tsv
genderator/data/surnames_ine.tsv
genderator311-0.2.8.1.dist-info/licenses/LICENSE
genderator311-0.2.8.1.dist-info/METADATA
genderator311-0.2.8.1.dist-info/WHEEL
genderator311-0.2.8.1.dist-info/top_level.txt
genderator311-0.2.8.1.dist-info/RECORD
