Metadata-Version: 2.4
Name: genderator311
Version: 0.2.8.1
Summary: Python library to guess gender given a spanish full name for Python 3.11+
Home-page: https://github.com/xumixprto/genderator311
Download-URL: https://github.com/xumixprto/genderator311/archive/refs/tags/v0.2.8.1.tar.gz
Author: David Moreno-Garcia (mantained by Diego Delgado)
Author-email: ddelgado.1405@gmail.com
License: MIT
Keywords: gender,guess,spanish,name
Classifier: Development Status :: 4 - Beta
Classifier: Topic :: Software Development :: Libraries
Classifier: Intended Audience :: Developers
Classifier: Intended Audience :: Education
Classifier: Intended Audience :: Information Technology
Classifier: License :: OSI Approved :: MIT License
Classifier: Programming Language :: Python
Classifier: Programming Language :: Python :: 3
License-File: LICENSE
Requires-Dist: unidecode==1.4.0
Dynamic: author
Dynamic: author-email
Dynamic: classifier
Dynamic: description
Dynamic: download-url
Dynamic: home-page
Dynamic: keywords
Dynamic: license
Dynamic: license-file
Dynamic: requires-dist
Dynamic: summary
